[
  {
    "record_id": "6f3af298-f4d2-4ce0-a4de-b2ad7ffd4c96",
    "provider_name": "Greenline Old Delhi Medical Centre",
    "license_number": "DL/MC/2018/01004",
    "risk_category": "Operational",
    "issue_description": "Critical staff shortage reported",
    "severity": "Low",
    "risk_score": 27,
    "last_detected": "2025-09-16T11:42:45Z",
    "source": "Simulated Monitoring Feed",
    "recommendation": "Hire temporary replacements and monitor shift load"
  },
  {
    "record_id": "42d6a570-61a6-4aab-83cc-b8fd61b49376",
    "provider_name": "Nova Old Delhi General Hospital",
    "license_number": "DL-HOSP-2023-1005",
    "risk_category": "Operational",
    "issue_description": "Critical staff shortage reported",
    "severity": "Medium",
    "risk_score": 47,
    "last_detected": "2025-09-08T11:42:45Z",
    "source": "Simulated Monitoring Feed",
    "recommendation": "Hire temporary replacements and monitor shift load"
  },
  {
    "record_id": "9c775980-45f9-4f2d-9875-e34032821248",
    "provider_name": "Aarogya Old Delhi Medical Centre",
    "license_number": "DL-HOSP-2018-1010",
    "risk_category": "Operational",
    "issue_description": "Critical staff shortage reported",
    "severity": "Medium",
    "risk_score": 49,
    "last_detected": "2025-08-19T11:42:45Z",
    "source": "Simulated Monitoring Feed",
    "recommendation": "Hire temporary replacements and monitor shift load"
  },
  {
    "record_id": "bfde2b53-07d1-4971-b921-9844a00c5f24",
    "provider_name": "Samarth Vadodara General Hospital",
    "license_number": "GJ/MC/2021/01011",
    "risk_category": "Operational",
    "issue_description": "Critical staff shortage reported",
    "severity": "Low",
    "risk_score": 24,
    "last_detected": "2025-10-05T11:42:45Z",
    "source": "Simulated Monitoring Feed",
    "recommendation": "Hire temporary replacements and monitor shift load"
  },
  {
    "record_id": "22b19de7-bb63-470f-95d5-0001daf943ae",
    "provider_name": "Saraswati Howrah Diagnostic Centre",
    "license_number": "WB/MC/2025/01017",
    "risk_category": "Operational",
    "issue_description": "Server downtime exceeded 4 hours",
    "severity": "Low",
    "risk_score": 20,
    "last_detected": "2025-08-10T11:42:45Z",
    "source": "Simulated Monitoring Feed",
    "recommendation": "Implement redundancy for high availability"
  },
  {
    "record_id": "d7aa0536-cd91-43cb-9446-3248d2cce0d3",
    "provider_name": "MediTrust Gurgaon General Hospital",
    "license_number": "HR/MC/2020/01018",
    "risk_category": "Operational",
    "issue_description": "Server downtime exceeded 4 hours",
    "severity": "Low",
    "risk_score": 23,
    "last_detected": "2025-10-05T11:42:45Z",
    "source": "Simulated Monitoring Feed",
    "recommendation": "Implement redundancy for high availability"
  },
  {
    "record_id": "2650fd35-ec8d-4ec9-a47d-b61e7fe4037d",
    "provider_name": "Fortis Howrah Clinic",
    "license_number": "WB/MC/2018/01020",
    "risk_category": "Operational",
    "issue_description": "Server downtime exceeded 4 hours",
    "severity": "Critical",
    "risk_score": 87,
    "last_detected": "2025-10-24T11:42:45Z",
    "source": "Simulated Monitoring Feed",
    "recommendation": "Implement redundancy for high availability"
  },
  {
    "record_id": "dd9bac46-58a1-4536-b4af-311c7c1c025b",
    "provider_name": "HealthFirst Old Delhi Medical Centre",
    "license_number": "DL-HOSP-2020-1022",
    "risk_category": "Operational",
    "issue_description": "Network outage affected critical systems",
    "severity": "Medium",
    "risk_score": 49,
    "last_detected": "2025-08-20T11:42:45Z",
    "source": "Simulated Monitoring Feed",
    "recommendation": "Contact ISP and enable failover route"
  },
  {
    "record_id": "3ee5556b-e90c-4de8-9c47-a46073cd9ed0",
    "provider_name": "Greenline Faridabad Health Centre",
    "license_number": "HR/MC/2022/01023",
    "risk_category": "Operational",
    "issue_description": "Backup recovery test failed",
    "severity": "Critical",
    "risk_score": 88,
    "last_detected": "2025-09-10T11:42:45Z",
    "source": "Simulated Monitoring Feed",
    "recommendation": "Verify DR plan and conduct drill"
  },
  {
    "record_id": "f831dcc4-b71a-434a-bfc0-4f7faa7f5d8e",
    "provider_name": "Samarth Howrah Diagnostic Centre",
    "license_number": "WB-LIC-2024-01028",
    "risk_category": "Operational",
    "issue_description": "Backup recovery test failed",
    "severity": "High",
    "risk_score": 77,
    "last_detected": "2025-10-06T11:42:45Z",
    "source": "Simulated Monitoring Feed",
    "recommendation": "Verify DR plan and conduct drill"
  },
  {
    "record_id": "c9138487-06cb-44f9-af0a-7b875a9ce6d1",
    "provider_name": "Samarth Surat Clinic",
    "license_number": "GJ/MC/2019/01029",
    "risk_category": "Operational",
    "issue_description": "Backup recovery test failed",
    "severity": "Medium",
    "risk_score": 44,
    "last_detected": "2025-09-06T11:42:45Z",
    "source": "Simulated Monitoring Feed",
    "recommendation": "Verify DR plan and conduct drill"
  },
  {
    "record_id": "c745cdf9-80d1-45dc-87e2-5b235c406a0b",
    "provider_name": "Anand Amritsar Diagnostic Centre",
    "license_number": "PBMED20251034",
    "risk_category": "Operational",
    "issue_description": "Backup recovery test failed",
    "severity": "Medium",
    "risk_score": 59,
    "last_detected": "2025-10-20T11:42:45Z",
    "source": "Simulated Monitoring Feed",
    "recommendation": "Verify DR plan and conduct drill"
  },
  {
    "record_id": "4874bedd-2227-48fa-8caf-0a9dbb8f54a4",
    "provider_name": "Lifeline Chennai Medical Centre",
    "license_number": "TN-LIC-2025-01045",
    "risk_category": "Operational",
    "issue_description": "Network outage affected critical systems",
    "severity": "High",
    "risk_score": 73,
    "last_detected": "2025-10-30T11:42:45Z",
    "source": "Simulated Monitoring Feed",
    "recommendation": "Contact ISP and enable failover route"
  },
  {
    "record_id": "985f84c4-c7c4-464a-aed8-2d0c232005df",
    "provider_name": "Aarogya Old Delhi Community Hospital",
    "license_number": "DL-LIC-2021-01047",
    "risk_category": "Operational",
    "issue_description": "Network outage affected critical systems",
    "severity": "Medium",
    "risk_score": 48,
    "last_detected": "2025-08-21T11:42:45Z",
    "source": "Simulated Monitoring Feed",
    "recommendation": "Contact ISP and enable failover route"
  },
  {
    "record_id": "c3e569d8-a261-4a1a-84f0-592b06cc00b1",
    "provider_name": "Samarth Pune General Hospital",
    "license_number": "MH-LIC-2021-01049",
    "risk_category": "Operational",
    "issue_description": "Backup recovery test failed",
    "severity": "Low",
    "risk_score": 39,
    "last_detected": "2025-09-03T11:42:45Z",
    "source": "Simulated Monitoring Feed",
    "recommendation": "Verify DR plan and conduct drill"
  }
]